CHANGES.txt
MANIFEST.in
README.txt
setup.py
two/__init__.py
two.bootstrap.egg-info/PKG-INFO
two.bootstrap.egg-info/SOURCES.txt
two.bootstrap.egg-info/dependency_links.txt
two.bootstrap.egg-info/entry_points.txt
two.bootstrap.egg-info/namespace_packages.txt
two.bootstrap.egg-info/not-zip-safe
two.bootstrap.egg-info/requires.txt
two.bootstrap.egg-info/top_level.txt
two/bootstrap/__init__.py
two/bootstrap/paginator.py
two/bootstrap/static/css/bootstrap-theme.css
two/bootstrap/static/css/bootstrap-theme.min.css
two/bootstrap/static/css/bootstrap.css
two/bootstrap/static/css/bootstrap.min.css
two/bootstrap/static/css/twool-bootstrap.css
two/bootstrap/static/fonts/glyphicons-halflings-regular.eot
two/bootstrap/static/fonts/glyphicons-halflings-regular.svg
two/bootstrap/static/fonts/glyphicons-halflings-regular.ttf
two/bootstrap/static/fonts/glyphicons-halflings-regular.woff
two/bootstrap/static/js/bootstrap.js
two/bootstrap/static/js/bootstrap.min.js
two/bootstrap/static/js/vendor/jquery-1.10.1.min.js
two/bootstrap/static/js/vendor/modernizr-2.6.2-respond-1.1.0.min.js
two/bootstrap/templates/404.html
two/bootstrap/templates/500.html
two/bootstrap/templates/two.bootstrap/base.html
two/bootstrap/templates/two.bootstrap/bootstrap-form.html
two/bootstrap/templates/two.bootstrap/breadcrumb.html
two/bootstrap/templates/two.bootstrap/pagination.html
two/bootstrap/templates/userena/base_userena.html
two/bootstrap/templates/userena/base_userena_nav.html
two/bootstrap/templates/userena/email_form.html
two/bootstrap/templates/userena/password_form.html
two/bootstrap/templates/userena/password_reset_confirm_form.html
two/bootstrap/templates/userena/password_reset_form.html
two/bootstrap/templates/userena/profile_detail.html
two/bootstrap/templates/userena/profile_form.html
two/bootstrap/templates/userena/signin_form.html
two/bootstrap/templates/userena/signup_form.html
two/bootstrap/templates/userena/two_userena.html
two/bootstrap/templates/userena/userena_well_form.html
two/bootstrap/templatetags/__init__.py
two/bootstrap/templatetags/fieldtype.py