Metadata-Version: 1.1
Name: two.bootstrap
Version: 1.0
Summary: bootstrap templates for two
Home-page: http://github.com/iivvoo/two.bootstrap
Author: Ivo van der Wijk
Author-email: two@in.m3r.nl
License: BSD
Platform: UNKNOWN
Classifier: Programming Language :: Python
